odoo/addons/account_invoice_overdue_reminder/README.rst
odoo/addons/account_invoice_overdue_reminder/__init__.py
odoo/addons/account_invoice_overdue_reminder/__manifest__.py
odoo/addons/account_invoice_overdue_reminder/hooks.py
odoo/addons/account_invoice_overdue_reminder/data/mail_template.xml
odoo/addons/account_invoice_overdue_reminder/data/overdue_reminder_result.xml
odoo/addons/account_invoice_overdue_reminder/i18n/account_invoice_overdue_reminder.pot
odoo/addons/account_invoice_overdue_reminder/i18n/ca.po
odoo/addons/account_invoice_overdue_reminder/i18n/de.po
odoo/addons/account_invoice_overdue_reminder/i18n/es.po
odoo/addons/account_invoice_overdue_reminder/i18n/fr.po
odoo/addons/account_invoice_overdue_reminder/i18n/it.po
odoo/addons/account_invoice_overdue_reminder/i18n/nl.po
odoo/addons/account_invoice_overdue_reminder/i18n/pt.po
odoo/addons/account_invoice_overdue_reminder/i18n/pt_BR.po
odoo/addons/account_invoice_overdue_reminder/models/__init__.py
odoo/addons/account_invoice_overdue_reminder/models/account_invoice_overdue_reminder.py
odoo/addons/account_invoice_overdue_reminder/models/account_move.py
odoo/addons/account_invoice_overdue_reminder/models/overdue_reminder_action.py
odoo/addons/account_invoice_overdue_reminder/models/overdue_reminder_result.py
odoo/addons/account_invoice_overdue_reminder/models/res_company.py
odoo/addons/account_invoice_overdue_reminder/models/res_partner.py
odoo/addons/account_invoice_overdue_reminder/readme/CONFIGURATION.rst
odoo/addons/account_invoice_overdue_reminder/readme/CONTRIBUTORS.md
odoo/addons/account_invoice_overdue_reminder/readme/DESCRIPTION.md
odoo/addons/account_invoice_overdue_reminder/readme/HISTORY.md
odoo/addons/account_invoice_overdue_reminder/readme/USAGE.md
odoo/addons/account_invoice_overdue_reminder/security/ir.model.access.csv
odoo/addons/account_invoice_overdue_reminder/security/ir_rule.xml
odoo/addons/account_invoice_overdue_reminder/static/description/icon.png
odoo_addon_account_invoice_overdue_reminder-18.0.1.2.0.4.dist-info/METADATA
odoo_addon_account_invoice_overdue_reminder-18.0.1.2.0.4.dist-info/WHEEL
odoo_addon_account_invoice_overdue_reminder-18.0.1.2.0.4.dist-info/top_level.txt
odoo_addon_account_invoice_overdue_reminder-18.0.1.2.0.4.dist-info/RECORD
